amortizer/__init__.py
amortizer/generator.py
amortizer-0.0.4.dist-info/LICENSE
amortizer-0.0.4.dist-info/METADATA
amortizer-0.0.4.dist-info/WHEEL
amortizer-0.0.4.dist-info/top_level.txt
amortizer-0.0.4.dist-info/RECORD
