Metadata-Version: 2.1
Name: amortizer
Version: 0.0.4
Summary: Simple package for generating loan amortization table and summary
Home-page: https://github.com/vlntsolo/amortizer
Author: Valentine Solonechnyi
Author-email: valentinesolo@gmail.com
License: UNKNOWN
Platform: UNKNOWN
Classifier: Programming Language :: Python :: 3
Classifier: License :: OSI Approved :: MIT License
Classifier: Operating System :: OS Independent
Classifier: Topic :: Office/Business :: Financial
Classifier: Topic :: Office/Business :: Financial :: Accounting
Classifier: Topic :: Office/Business :: Financial :: Investment
Requires-Python: >=3.7
Requires-Dist: pandas (>=1.2.4)
